unimail_py_sdk/__init__.py
unimail_py_sdk/Client.py
unimail_py_sdk-0.1.2.dist-info/LICENSE
unimail_py_sdk-0.1.2.dist-info/METADATA
unimail_py_sdk-0.1.2.dist-info/WHEEL
unimail_py_sdk-0.1.2.dist-info/RECORD
