Metadata-Version: 2.1
Name: unimail-py-sdk
Version: 0.1.2
Summary: This is a Python SDK for Unimail. Quickly integrate into your project
Home-page: https://github.com/i-curve/unimail-py-sdk
License: BSD-3-Clause
Keywords: unimail,unimail-py-sdk
Author: i-curve
Author-email: i-curve@qq.com
Requires-Python: >=3.12,<4.0
Classifier: License :: OSI Approved :: BSD License
Classifier: Programming Language :: Python :: 3
Classifier: Programming Language :: Python :: 3.12
Classifier: Programming Language :: Python :: 3.13
Requires-Dist: requests (>=2.32.3,<3.0.0)
Project-URL: Bug Tracker, https://github.com/i-curve/unimail-py-sdk/issues
Project-URL: Documentation, https://github.com/i-curve/unimail-py-sdk
Project-URL: Repository, https://github.com/i-curve/unimail-py-sdk
